ssh_auto_upgrade/__init__.py
ssh_auto_upgrade/arg.py
ssh_auto_upgrade/argument_validator.py
ssh_auto_upgrade/compile.py
ssh_auto_upgrade/daemon_loop.py
ssh_auto_upgrade/dependencies.py
ssh_auto_upgrade/dependency_constants.py
ssh_auto_upgrade/downloader.py
ssh_auto_upgrade/installer.py
ssh_auto_upgrade/installer_file_manager.py
ssh_auto_upgrade/installer_service_detector.py
ssh_auto_upgrade/installer_service_manager.py
ssh_auto_upgrade/legacy_cleaner.py
ssh_auto_upgrade/logger.py
ssh_auto_upgrade/main.py
ssh_auto_upgrade/mirror_checker.py
ssh_auto_upgrade/port_checker.py
ssh_auto_upgrade/service_detector.py
ssh_auto_upgrade/service_manager.py
ssh_auto_upgrade/service_registrar.py
ssh_auto_upgrade/ssh_config_manager.py
ssh_auto_upgrade/ssh_config_manager_status.py
ssh_auto_upgrade/systemd_checker.py
ssh_auto_upgrade/temp_account_validator.py
ssh_auto_upgrade/time_checker.py
ssh_auto_upgrade/version_detector.py
ssh_auto_upgrade-1.1.5.dist-info/licenses/LICENSE
ssh_auto_upgrade-1.1.5.dist-info/METADATA
ssh_auto_upgrade-1.1.5.dist-info/WHEEL
ssh_auto_upgrade-1.1.5.dist-info/entry_points.txt
ssh_auto_upgrade-1.1.5.dist-info/top_level.txt
ssh_auto_upgrade-1.1.5.dist-info/RECORD
