Metadata-Version: 2.4
Name: ssh-auto-upgrade
Version: 1.1.5
Summary: 自动检测和升级OpenSSH的工具
Author-email: 坐公交也用券 <liumou.site@qq.com>
License: MIT
Project-URL: Homepage, https://gitee.com/liumou_site/ssh-automatic-upgrade
Project-URL: Repository, https://gitee.com/liumou_site/ssh-automatic-upgrade
Project-URL: Bug Reports, https://gitee.com/liumou_site/ssh-automatic-upgrade/issues
Classifier: Development Status :: 4 - Beta
Classifier: Intended Audience :: System Administrators
Classifier: License :: OSI Approved :: MIT License
Classifier: Operating System :: POSIX :: Linux
Classifier: Programming Language :: Python :: 3
Classifier: Programming Language :: Python :: 3.6
Classifier: Programming Language :: Python :: 3.7
Classifier: Programming Language :: Python :: 3.8
Classifier: Programming Language :: Python :: 3.9
Classifier: Programming Language :: Python :: 3.10
Classifier: Programming Language :: Python :: 3.11
Classifier: Programming Language :: Python :: 3.12
Classifier: Programming Language :: Python :: 3.13
Classifier: Programming Language :: Python :: 3.14
Classifier: Topic :: System :: Systems Administration
Requires-Python: >=3.6
License-File: LICENSE
Requires-Dist: requests>=2.25.0
Requires-Dist: beautifulsoup4>=4.9.0
Requires-Dist: systemd-python>=234
Requires-Dist: dbus-python>=1.2.0
Requires-Dist: plpm-liumou-stable>=1.0.1
Requires-Dist: paramiko>=2.7.0
Dynamic: license-file
